ipfs_cid_v0-0.0.1.dist-info/METADATA
ipfs_cid_v0-0.0.1.dist-info/WHEEL
ipfs_cid_v0/__init__.py
ipfs_cid_v0/ipfs_cid_v0.cpython-38-x86_64-linux-gnu.so
ipfs_cid_v0-0.0.1.dist-info/RECORD
